airflow_livy/__init__.py
airflow_livy/batch_plugin.py
airflow_livy/session_plugin.py
airflow_livy_plugins-0.2.dist-info/LICENSE
airflow_livy_plugins-0.2.dist-info/METADATA
airflow_livy_plugins-0.2.dist-info/WHEEL
airflow_livy_plugins-0.2.dist-info/top_level.txt
airflow_livy_plugins-0.2.dist-info/RECORD
