Metadata-Version: 2.1
Name: airflow-livy-plugins
Version: 0.2
Summary: Plugins for Airflow to run Spark jobs via Livy: sessions and batches
Home-page: https://github.com/panovvv/airflow-livy-plugins
Author: Vadim Panov
Author-email: headcra6@gmail.com
License: MIT License
Platform: UNKNOWN
Requires-Python: >=3.7
